{"swagger": "2.0", "info": {"title": "drf-users api", "description": "This Django User Model is customised user model keeping in mind the practical need (esp. in India).", "termsOfService": "https://www.google.com/policies/terms/", "contact": {"email": "devs@101loop.com"}, "license": {"name": "GPL-3.0 License"}, "version": "v1"}, "host": "localhost:8000", "schemes": ["http"], "basePath": "/api/user", "consumes": ["application/json"], "produces": ["application/json"], "securityDefinitions": {"Basic": {"type": "basic"}}, "security": [{"Basic": []}], "paths": {"/account/": {"get": {"operationId": "account_read", "description": "Fetch Account Details", "parameters": [], "responses": {"200": {"description": "", "schema": {"$ref": "#/definitions/User"}}}, "tags": ["account"]}, "put": {"operationId": "account_update", "description": "Update all details", "parameters": [{"name": "data", "in": "body", "required": true, "schema": {"$ref": "#/definitions/User"}}], "responses": {"200": {"description": "", "schema": {"$ref": "#/definitions/User"}}}, "tags": ["account"]}, "patch": {"operationId": "account_partial_update", "description": "Update some details", "parameters": [{"name": "data", "in": "body", "required": true, "schema": {"$ref": "#/definitions/User"}}], "responses": {"200": {"description": "", "schema": {"$ref": "#/definitions/User"}}}, "tags": ["account"]}, "parameters": []}, "/isunique/": {"post": {"operationId": "isunique_create", "description": "Overrides post method to validate serialized data", "parameters": [], "responses": {"201": {"description": ""}}, "tags": ["isunique"]}, "parameters": []}, "/login/": {"post": {"operationId": "login_create", "description": "Process a login request via username/password.", "parameters": [], "responses": {"201": {"description": ""}}, "tags": ["login"]}, "parameters": []}, "/otp/": {"post": {"operationId": "otp_create", "description": "Overrides post method to validate serialized data", "parameters": [], "responses": {"201": {"description": ""}}, "tags": ["otp"]}, "parameters": []}, "/otpreglogin/": {"post": {"operationId": "otpreglogin_create", "description": "Overrides post method to validate serialized data", "parameters": [], "responses": {"201": {"description": ""}}, "tags": ["otpreglogin"]}, "parameters": []}, "/password/reset/": {"post": {"operationId": "password_reset_create", "description": "Overrides post method to validate OTP and reset password", "parameters": [], "responses": {"201": {"description": ""}}, "tags": ["password"]}, "parameters": []}, "/refresh-token/": {"post": {"operationId": "refresh-token_create", "description": "Process request to generate new access token using\nrefresh token.", "parameters": [{"name": "data", "in": "body", "required": true, "schema": {"$ref": "#/definitions/TokenRefresh"}}], "responses": {"201": {"description": "", "schema": {"$ref": "#/definitions/TokenRefresh"}}}, "tags": ["refresh-token"]}, "parameters": []}, "/register/": {"post": {"operationId": "register_create", "summary": "Register View", "description": "Register a new user to the system.\nThe data required are username, email, name, password and mobile (optional).", "parameters": [{"name": "data", "in": "body", "required": true, "schema": {"$ref": "#/definitions/User"}}], "responses": {"201": {"description": "", "schema": {"$ref": "#/definitions/User"}}}, "tags": ["register"]}, "parameters": []}, "/upload-image/": {"post": {"operationId": "upload-image_create", "description": "Validate serializer and upload user profile image", "parameters": [], "responses": {"201": {"description": ""}}, "tags": ["upload-image"]}, "parameters": []}}, "definitions": {"User": {"required": ["username", "name", "email", "password"], "type": "object", "properties": {"id": {"title": "ID", "type": "integer", "readOnly": true}, "username": {"title": "Unique UserName", "type": "string", "maxLength": 254, "minLength": 1}, "name": {"title": "Full Name", "type": "string", "maxLength": 500, "minLength": 1}, "email": {"title": "Email Address", "type": "string", "format": "email", "maxLength": 254, "minLength": 1}, "mobile": {"title": "Mobile Number", "type": "string", "maxLength": 150, "x-nullable": true}, "password": {"title": "Password", "type": "string", "maxLength": 128, "minLength": 1}, "is_superuser": {"title": "Superuser status", "description": "Designates that this user has all permissions without explicitly assigning them.", "type": "boolean", "readOnly": true}, "is_staff": {"title": "Staff Status", "type": "boolean", "readOnly": true}}}, "TokenRefresh": {"required": ["refresh"], "type": "object", "properties": {"refresh": {"title": "Refresh", "type": "string", "minLength": 1}, "access": {"title": "Access", "type": "string", "readOnly": true, "minLength": 1}}}}}